ipio/__init__.py
ipio/api_method.py
ipio/config_field.py
ipio/device.py
ipio/exceptions.py
ipio/ipio.py
ipio/pin_state.py
test/__init__.py
test/test_example.py
test/test_suite.py
ipio-26.2876.2308.dist-info/LICENSE
ipio-26.2876.2308.dist-info/METADATA
ipio-26.2876.2308.dist-info/WHEEL
ipio-26.2876.2308.dist-info/top_level.txt
ipio-26.2876.2308.dist-info/RECORD
