Metadata-Version: 2.1
Name: ipio
Version: 26.2876.2308
Summary: IPIO Python Library
Home-page: https://ipio.readthedocs.io/
Author: Kemal Çelikel
Author-email: kcelikel@eventgates.com
Classifier: Programming Language :: Python :: 3
Classifier: License :: OSI Approved :: MIT License
Classifier: Operating System :: OS Independent
Requires-Python: >=3.8
License-File: LICENSE
